intecomm_rando/__init__.py
intecomm_rando/apps.py
intecomm_rando/constants.py
intecomm_rando/exceptions.py
intecomm_rando/group_eligibility.py
intecomm_rando/group_identifier.py
intecomm_rando/randomize_group.py
intecomm_rando/randomizers.py
intecomm_rando/urls.py
intecomm_rando/utils.py
intecomm_rando/migrations/0001_initial.py
intecomm_rando/migrations/0002_alter_historicalregisteredgroup_group_identifier_and_more.py
intecomm_rando/migrations/0003_alter_randomizationlist_options_and_more.py
intecomm_rando/migrations/0004_alter_historicalrandomizationlist_device_created_and_more.py
intecomm_rando/migrations/0005_alter_randomizationlist_options_and_more.py
intecomm_rando/migrations/0006_alter_registeredgroup_options.py
intecomm_rando/migrations/0007_alter_historicalregisteredgroup_site_and_more.py
intecomm_rando/migrations/__init__.py
intecomm_rando/models/__init__.py
intecomm_rando/models/randomization_list.py
intecomm_rando/models/registered_group.py
intecomm_rando/models/signals.py
intecomm_rando/tests/__init__.py
intecomm_rando/tests/models.py
intecomm_rando/tests/test_settings.py
intecomm_rando/tests/etc/randomization_list.csv
intecomm_rando/tests/etc/user-aes-local.key
intecomm_rando/tests/etc/user-aes-restricted.key
intecomm_rando/tests/etc/user-rsa-local-private.pem
intecomm_rando/tests/etc/user-rsa-local-public.pem
intecomm_rando/tests/etc/user-rsa-restricted-private.pem
intecomm_rando/tests/etc/user-rsa-restricted-public.pem
intecomm_rando/tests/etc/user-salt-local.key
intecomm_rando/tests/etc/user-salt-restricted.key
intecomm_rando/tests/tests/__init__.py
intecomm_rando/tests/tests/test_rando_group.py
intecomm_rando-0.1.26.dist-info/AUTHORS
intecomm_rando-0.1.26.dist-info/LICENSE
intecomm_rando-0.1.26.dist-info/METADATA
intecomm_rando-0.1.26.dist-info/WHEEL
intecomm_rando-0.1.26.dist-info/top_level.txt
intecomm_rando-0.1.26.dist-info/RECORD
